Workbook

Sheet 03 Data VAT Group 1
A1: VAT Group 1 — Entity A and Entity B
A2: Blue = hardcoded values to load. VAT amounts calculated by formula. No inter-entity transactions in this dataset.
A4: AR — Output VAT
A5: Ref | B5: VAT Group | C5: Entity | D5: Description | E5: Net (AED) | F5: Code as extracted | G5: Rate applied | H5: Output VAT (AED) | I5: Exception type & outcome | J5: How this figure is built
A6: AR-A-001 | B6: Group 1 | C6: Entity A | D6: Service revenue | E6: 2000000 | F6: SR 5% | G6: 0.05 | H6: =E6*G6 -> 100000 | I6: None — clean | J6: 2,000,000 x 5% = 100,000. Posted correctly at source, so GL and working agree.
A7: AR-A-005 | B7: Group 1 | C7: Entity A | D7: Consultancy fee (sale to customer) | E7: 200000 | F7: Exempt (incorrect) | G7: 0.05 | H7: =E7*G7 -> 10000 | I7: 1. Incorrect VAT — ACCEPTED | J7: Source posted this as Exempt, so the GL carries NIL output VAT. The recommendation is accepted, so the working carries 200,000 x 5% = 10,000 and a notification is issued to the source owner. Note: this is a SALE, so 10,000 was under-billed to the customer — see Q&A sheet 06.
A8: AR-A-003 | B8: Group 1 | C8: Entity A | D8: Facility fees | E8: 300000 | F8: No VAT code on extract | G8: 0 | H8: =E8*G8 -> 0 | I8: 2. No VAT — REJECTED | J8: Platform recommends SR 5% (15,000). The recommendation is REJECTED on review — the supply is confirmed out of scope — so the ERP treatment stands and output VAT remains NIL. GL and working therefore agree.
A9: AR-B-001 | B9: Group 1 | C9: Entity B | D9: Service revenue | E9: 1200000 | F9: SR 5% | G9: 0.05 | H9: =E9*G9 -> 60000 | I9: None — clean | J9: 1,200,000 x 5% = 60,000. Entity B's only output VAT row.
A11: AP — Input VAT
A12: Ref | B12: VAT Group | C12: Entity | D12: Description | E12: Net (AED) | F12: Input VAT on extract (AED) | G12: Rate | H12: Recoverable (AED) | I12: Exception type & outcome | J12: How this figure is built
A13: AP-A-101 | B13: Group 1 | C13: Entity A | D13: Operating supplies | E13: 800000 | F13: =E13*G13 -> 40000 | G13: 0.05 | H13: =IF(I13="3. Duplicate — EMERGENCY ADJUST",0,F13) -> 40000 | I13: None — clean | J13: 800,000 x 5% = 40,000. Entity A's only input VAT row, so GL and working both show 40,000.
A14: AP-B-101 | B14: Group 1 | C14: Entity B | D14: Capital purchase | E14: 2000000 | F14: =E14*G14 -> 100000 | G14: 0.05 | H14: =IF(I14="3. Duplicate — EMERGENCY ADJUST",0,F14) -> 100000 | I14: None — clean | J14: 2,000,000 x 5% = 100,000.
A15: AP-B-103 | B15: Group 1 | C15: Entity B | D15: Maintenance — DUPLICATE record | E15: 400000 | F15: =E15*G15 -> 20000 | G15: 0.05 | H15: =IF(I15="3. Duplicate — EMERGENCY ADJUST",0,F15) -> 0 | I15: 3. Duplicate — EMERGENCY ADJUST | J15: 400,000 x 5% = 20,000 sits in the source and therefore in the GL. Flagged as a duplicate and removed in the VAT platform ONLY so filing is not delayed; the source system has not been corrected and is flagged for follow-up. This single row is the 20,000 GL difference on Entity B input.
A17: GL to sub-ledger reconciliation — control-account total level only
A18: GL balance = the BEFORE picture: what the source system actually posted. VAT working = the AFTER picture: what the platform carries once accepted corrections and emergency adjustments are applied. Both differences below are explained.
A19: VAT Group | B19: Entity | C19: Control account | D19: GL balance (AED) | E19: VAT working (AED) | F19: Difference (AED) | G19: Classification | H19: GL balance is built from | I19: VAT working is built from | J19: Outcome route
A20: Group 1 | B20: Entity A | C20: VAT Output Control | D20: 100000 | E20: ='05 Expected Results'!B5 -> 110000 | F20: =ABS(D20-E20) -> 10000 | G20: Explained — Incorrect VAT correction accepted and notified to source, pending correction at source | H20: AR-A-001 100,000 only. AR-A-005 posted as Exempt and AR-A-003 posted with no VAT, so neither carries output VAT at source. | I20: AR-A-001 100,000 + AR-A-005 accepted correction 10,000 = 110,000. AR-A-003 remains nil because the recommendation was rejected. | J20: ACCEPT — notification issued, awaiting source correction
A21: Group 1 | B21: Entity A | C21: VAT Input Control | D21: 40000 | E21: ='05 Expected Results'!B6 -> 40000 | F21: =ABS(D21-E21) -> 0 | G21: Agrees — no difference | H21: AP-A-101 40,000. | I21: AP-A-101 40,000. | J21: n/a
A22: Group 1 | B22: Entity B | C22: VAT Output Control | D22: 60000 | E22: ='05 Expected Results'!C5 -> 60000 | F22: =ABS(D22-E22) -> 0 | G22: Agrees — no difference | H22: AR-B-001 60,000. | I22: AR-B-001 60,000. | J22: n/a
A23: Group 1 | B23: Entity B | C23: VAT Input Control | D23: 120000 | E23: ='05 Expected Results'!C6 -> 100000 | F23: =ABS(D23-E23) -> 20000 | G23: Explained — duplicate removed in the VAT platform only under Emergency Adjust; source not yet corrected | H23: AP-B-101 100,000 + AP-B-103 duplicate 20,000 = 120,000. The duplicate is still in the source. | I23: AP-B-101 100,000 only. The duplicate of 20,000 has been adjusted out in the platform. | J23: EMERGENCY ADJUST — source flagged for follow-up; on review, route to ACCEPT and notify source
A25: Reconciliation is at control-account total level per the agreed design, not transaction level. Drill-down to the underlying transaction is available where investigation is needed.
A26: Plus ~200 clean AR and ~150 clean AP generated records per entity as volume padding. These do not affect any figure in sheet 05.

Sheet 04 Data VAT Group 2
A1: VAT Group 2 — Entity C
A2: Three lines only. Purpose: prove the solution is multi-group and demonstrate a net REFUND position. No exceptions in this group.
A4: AR — Output VAT
A5: Ref | B5: VAT Group | C5: Entity | D5: Description | E5: Net (AED) | F5: Code as extracted | G5: Rate applied | H5: Output VAT (AED) | I5: Note
A6: AR-C-001 | B6: Group 2 | C6: Entity C | D6: Service revenue | E6: 800000 | F6: SR 5% | G6: 0.05 | H6: =E6*G6 -> 40000 | I6: Clean. 800,000 x 5% = 40,000.
A7: AR-C-002 | B7: Group 2 | C7: Entity C | D7: Export of services | E7: 200000 | F7: ZR 0% | G7: 0 | H7: =E7*G7 -> 0 | I7: Zero-rated, so nil output VAT. Included to show a second VAT treatment on screen.
D8: Total output VAT — VAT Group 2 | H8: =SUM(H6:H7) -> 40000
A10: AP — Input VAT
A11: Ref | B11: VAT Group | C11: Entity | D11: Description | E11: Net (AED) | F11: Input VAT (AED) | G11: Rate | H11: Recoverable (AED) | I11: Note
A12: AP-C-101 | B12: Group 2 | C12: Entity C | D12: Capital purchase | E12: 1200000 | F12: =E12*G12 -> 60000 | G12: 0.05 | H12: =F12 -> 60000 | I12: Clean. 1,200,000 x 5% = 60,000. Large capital spend is what drives the group into a refund position.
A14: VAT Group 2 result | E14: Amount (AED) | I14: Note
A15: Output VAT | E15: =H6+H7 -> 40000 | I15: AR-C-001 40,000 + AR-C-002 nil.
A16: Input VAT | E16: =H12 -> 60000 | I16: AP-C-101 60,000.
A17: NET POSITION | E17: =E15-E16 -> -20000 | I17: Net REFUND of 20,000. Demonstrates the refund request and tracking screen without building further transaction detail.
A19: VAT Group 3 is not built. It appears only as a summary line on the dashboard (see sheet 05).

Sheet 05 Expected Results
A1: Expected Results — Every Screen Must Foot To This
A2: Final filed position after all three exception outcomes are applied. No inter-entity elimination in this dataset.
A4: Line | B4: Entity A (AED) | C4: Entity B (AED) | D4: VAT Group 1 (AED) | E4: Note | F4: How the figure is built
A5: Output VAT | B5: =SUMIFS('03 Data VAT Group 1'!$H$6:$H$9,'03 Data VAT Group 1'!$C$6:$C$9,"Entity A") -> 110000 | C5: =SUMIFS('03 Data VAT Group 1'!$H$6:$H$9,'03 Data VAT Group 1'!$C$6:$C$9,"Entity B") -> 60000 | D5: =B5+C5 -> 170000 | E5: AR-A-005 included at its accepted corrected value of 10,000. AR-A-003 remains nil — recommendation rejected. | F5: Entity A 110,000 (100,000 + 10,000 + nil) + Entity B 60,000 = 170,000.
A6: Input VAT (recoverable) | B6: =SUMIFS('03 Data VAT Group 1'!$H$13:$H$15,'03 Data VAT Group 1'!$C$13:$C$15,"Entity A") -> 40000 | C6: =SUMIFS('03 Data VAT Group 1'!$H$13:$H$15,'03 Data VAT Group 1'!$C$13:$C$15,"Entity B") -> 100000 | D6: =B6+C6 -> 140000 | E6: AP-B-103 excluded — duplicate removed under Emergency Adjust. | F6: Entity A 40,000 + Entity B 100,000 = 140,000.
A7: NET VAT POSITION | B7: =B5-B6 -> 70000 | C7: =C5-C6 -> -40000 | D7: =D5-D6 -> 30000 | E7: Entity B is a refund sitting inside a Group payable — the argument for group consolidation. | F7: 170,000 less 140,000 = 30,000 payable for VAT Group 1.
A8: Position | B8: =IF(B7>0,"PAYABLE","REFUND") -> PAYABLE | C8: =IF(C7>0,"PAYABLE","REFUND") -> REFUND | D8: =IF(D7>0,"PAYABLE","REFUND") -> PAYABLE | E8: On consolidation a message is issued to the ERP for the net payable (screen 3.3). | F8: Entity A 70,000 payable less Entity B 40,000 refund = 30,000 net payable.
A10: Exception outcomes and their effect on the figures
A11: Exception type | B11: Record | C11: Recommendation | D11: Outcome taken | E11: Effect on the return | F11: Effect on GL reconciliation
A12: 1. Incorrect VAT | B12: AR-A-005 | C12: Change Exempt to SR 5% (10,000) | D12: ACCEPT | E12: Output VAT increases by 10,000. | F12: Creates a 10,000 difference on Entity A output until the source is corrected.
A13: 2. No VAT | B13: AR-A-003 | C13: Apply SR 5% (15,000) | D13: REJECT | E13: No change — output VAT remains nil. | F13: No difference. GL and working agree because the ERP treatment stands.
A14: 3. Duplicate data | B14: AP-B-103 | C14: Remove duplicate input VAT (20,000) | D14: EMERGENCY ADJUST | E14: Input VAT reduces by 20,000. | F14: Creates a 20,000 difference on Entity B input; source not yet corrected and flagged for follow-up.
A16: All VAT Groups — dashboard summary (screen 3.5)
A17: VAT Group | B17: Output VAT (AED) | C17: Input VAT (AED) | D17: Net (AED) | E17: Position | F17: Note
A18: VAT Group 1 (Entity A + Entity B) | B18: =D5 -> 170000 | C18: =D6 -> 140000 | D18: =D7 -> 30000 | E18: =IF(D18>0,"PAYABLE","REFUND") -> PAYABLE | F18: Built in full — drives all three scenarios.
A19: VAT Group 2 (Entity C) | B19: ='04 Data VAT Group 2'!E15 -> 40000 | C19: ='04 Data VAT Group 2'!E16 -> 60000 | D19: ='04 Data VAT Group 2'!E17 -> -20000 | E19: =IF(D19>0,"PAYABLE","REFUND") -> REFUND | F19: Three lines only. Net refund — demonstrates the refund tracking screen.
A20: VAT Group 3 | B20: 320000 | C20: 210000 | D20: =B20-C20 -> 110000 | E20: =IF(D20>0,"PAYABLE","REFUND") -> PAYABLE | F20: Summary line only, no transaction detail. Present for completeness against the 3 VAT Groups in the proposal.
